<?xml version="1.0" encoding="UTF-8"?>
<!DOCTYPE mapper PUBLIC "-//mybatis.org//DTD Mapper 3.0//EN" "http://mybatis.org/dtd/mybatis-3-mapper.dtd">
<mapper namespace="edu.utm.bd.mappers.ClienteMapper">
  <resultMap id="BaseResultMap" type="edu.utm.bd.domain.Cliente">
    <!--
      WARNING - @mbg.generated
      This element is automatically generated by MyBatis Generator, do not modify.
      This element was generated on Wed Apr 25 18:55:18 CDT 2018.
    -->
    <id column="IdCliente" jdbcType="INTEGER" property="idcliente" />
    <result column="CliTelefono" jdbcType="LONGVARCHAR" property="clitelefono" />
     <result column="CliNombre" jdbcType="LONGVARCHAR" property="clinombre" />
    <result column="CliApellidos" jdbcType="LONGVARCHAR" property="cliapellidos" />
    <result column="CliDireccion" jdbcType="LONGVARCHAR" property="clidireccion" />
  </resultMap>
  
  <select id="findAllClientes" resultMap="BaseResultMap">
		SELECT * FROM CLIENTE 
  </select>
  
  <insert id="insertCliente" parameterType="edu.utm.bd.domain.Cliente">
  		INSERT INTO CLIENTE (clinombre,cliapellidos,clitelefono,clidireccion) VALUES(#{clinombre},#{cliapellidos},
  		#{clitelefono},#{clidireccion})
  </insert>
  
  <select id="findOneCliente" parameterType="edu.utm.bd.domain.Cliente" resultMap="BaseResultMap">
  		SELECT cliente.* FROM CLIENTE
  		WHERE idcliente = #{idcliente}
  </select>
  
  <update id="updateCliente" parameterType="edu.utm.bd.domain.Cliente">
	UPDATE CLIENTE SET
		clinombre = #{clinombre}, cliapellidos = #{cliapellidos},
		clidireccion = #{clidireccion}, clitelefono = #{clitelefono} where idcliente = #{idcliente}
  </update>
  
 <!--  <delete id="deleteOneCliente" parameterType="edu.utm.bd.domain.Cliente">
  		DELETE FROM CLIENTE WHERE idcliente = #{idcliente}
  </delete> -->
</mapper>